project_6127/__init__.py
project_6127/static.py
project_6127/data/__init__.py
project_6127/data/preprocessing.py
project_6127/evaluation/__init__.py
project_6127/evaluation/evaluator.py
project_6127/evaluation/pycocoevalcap/__init__.py
project_6127/evaluation/pycocoevalcap/bleu/__init__.py
project_6127/evaluation/pycocoevalcap/bleu/bleu.py
project_6127/evaluation/pycocoevalcap/bleu/bleu_scorer.py
project_6127/evaluation/pycocoevalcap/cider/__init__.py
project_6127/evaluation/pycocoevalcap/cider/cider.py
project_6127/evaluation/pycocoevalcap/cider/cider_scorer.py
project_6127/evaluation/pycocoevalcap/meteor/__init__.py
project_6127/evaluation/pycocoevalcap/meteor/meteor.py
project_6127/evaluation/pycocoevalcap/rouge/__init__.py
project_6127/evaluation/pycocoevalcap/rouge/rouge.py
project_6127/model/__init__.py
project_6127/model/attention.py
project_6127/model/base.py
project_6127/model/decoder.py
project_6127/model/encoder.py
project_6127/model/networks.py
project_6127/model/predictor.py
project_6127/model/utils.py
project_6127-0.0.11.dist-info/METADATA
project_6127-0.0.11.dist-info/WHEEL
project_6127-0.0.11.dist-info/top_level.txt
project_6127-0.0.11.dist-info/RECORD
