Metadata-Version: 2.1
Name: project-6127
Version: 0.0.11
Summary: Package for AI6127 Project
Home-page: https://github.com/AiRiFiEd/project_6127
Author: yqlim
Author-email: yuanqing87@gmail.com
License: MIT
